{"Results":[{"MediaUrl":"http://www.freakingnews.com/pictures/37000/Lemon-Fish--37235.jpg","ContentType":"image/jpeg","Width":738,"Height":1200,"FileSize":114978},{"MediaUrl":"http://1.bp.blogspot.com/-McFN_b7M-lg/US2yHMzyPYI/AAAAAAAABh4/CoxyF2bfKeI/s1600/funny+fish.jpg","ContentType":"image/jpeg","Width":460,"Height":600,"FileSize":24812},{"MediaUrl":"http://th05.deviantart.net/fs9/PRE/i/2006/024/3/d/Freshwater_Fish_by_zoomanchoo.jpg","ContentType":"image/jpeg","Width":793,"Height":1007,"FileSize":171744},{"MediaUrl":"http://www.dfw.gov.mp/Downloads/Posters/Reef%20Fishes%20Poster.jpg","ContentType":"image/jpeg","Width":4301,"Height":6193,"FileSize":3981486},{"MediaUrl":"http://ellllen.files.wordpress.com/2010/06/poison-fish.jpg","ContentType":"image/jpeg","Width":2448,"Height":3264,"FileSize":2342108},{"MediaUrl":"http://www.unitedfisheries.co.nz/store/image/Fish/species_all.jpg","ContentType":"image/jpeg","Width":750,"Height":1049,"FileSize":237971},{"MediaUrl":"http://upload.wikimedia.org/wikipedia/commons/f/f2/GloFish.jpg","ContentType":"image/jpeg","Width":1323,"Height":1764,"FileSize":199723},{"MediaUrl":"http://www.desktopaper.com/wp-content/uploads/awesome-fish-fruits-sea-underwater.jpg","ContentType":"image/jpeg","Width":640,"Height":1136,"FileSize":85573},{"MediaUrl":"http://www.jesuspaintings.com/pictures/grass_hoppin.jpg","ContentType":"image/jpeg","Width":462,"Height":584,"FileSize":37661},{"MediaUrl":"http://discushans.files.wordpress.com/2010/06/discus_w_fry_21.jpg","ContentType":"image/jpeg","Width":768,"Height":1024,"FileSize":162644},{"MediaUrl":"http://mullowaydive.files.wordpress.com/2011/04/fish4.gif","ContentType":"image/gif","Width":500,"Height":753,"FileSize":282534},{"MediaUrl":"http://cyclopaedia.org/1819/ichthyology/1819fish1d.jpg","ContentType":"image/jpeg","Width":790,"Height":1000,"FileSize":99363},{"MediaUrl":"http://www.desktopaper.com/wp-content/uploads/cool-fish-wallpaper.jpg","ContentType":"image/jpeg","Width":640,"Height":960,"FileSize":71190},{"MediaUrl":"http://www.freefoto.com/images/09/07/09_07_52---Fish-and-Chips_web.jpg","ContentType":"image/jpeg","Width":400,"Height":600,"FileSize":35598},{"MediaUrl":"http://www.malaysia.com/blog/wp-content/uploads/2009/06/fish-tornado.jpg","ContentType":"image/jpeg","Width":768,"Height":1024,"FileSize":266193},{"MediaUrl":"http://valtenbergs.com/wp-content/uploads/2012/11/FourFishCover2.jpg","ContentType":"image/jpeg","Width":1875,"Height":2850,"FileSize":227021},{"MediaUrl":"http://www.freakingnews.com/Pictures/4/Flying-Fish.jpg","ContentType":"image/jpeg","Width":800,"Height":1145,"FileSize":265988},{"MediaUrl":"http://theconnectome.files.wordpress.com/2011/02/fish_brain.png","ContentType":"image/png","Width":690,"Height":1206,"FileSize":100814},{"MediaUrl":"http://www.captainjohnsfishing.com/wordpress/wp-content/uploads/2010/08/fish.gif","ContentType":"image/gif","Width":612,"Height":792,"FileSize":107866},{"MediaUrl":"http://www.mfma.com.au/wp-content/uploads/2011/04/Poster-Temperate-Fish.jpg","ContentType":"image/jpeg","Width":1134,"Height":1620,"FileSize":310379},{"MediaUrl":"http://2.bp.blogspot.com/-_biQNwrJtiM/UEJwpzCUG_I/AAAAAAAATo0/lPlErdc2Y78/s1600/fc+main+s.jpg","ContentType":"image/jpeg","Width":1279,"Height":1600,"FileSize":224339},{"MediaUrl":"http://2.bp.blogspot.com/_QT1bqiZWmN0/S6vYuhAyMeI/AAAAAAAABAw/trLkoE6tQAY/s1600/suesswasserfischen+-+German+names+for+fresh+water+fish.jpg","ContentType":"image/jpeg","Width":1084,"Height":1600,"FileSize":214066},{"MediaUrl":"http://www.bestcoloringpagesforkids.com/wp-content/uploads/2013/07/Fish-Coloring-Page.gif","ContentType":"image/gif","Width":718,"Height":957,"FileSize":16948},{"MediaUrl":"http://water.epa.gov/scitech/swguidance/fishshellfish/fishadvisories/images/one-fish-original_1.jpg","ContentType":"image/jpeg","Width":1800,"Height":2700,"FileSize":250049},{"MediaUrl":"http://www.murraymitchell.com/wp-content/uploads/2012/10/brightly_coloured_fish.jpeg","ContentType":"image/jpeg","Width":714,"Height":1024,"FileSize":364792},{"MediaUrl":"http://upload.wikimedia.org/wikipedia/commons/c/c1/Puffer_fish.jpg","ContentType":"image/jpeg","Width":960,"Height":1280,"FileSize":478963},{"MediaUrl":"http://mykingdomforafish.files.wordpress.com/2011/10/img_2385.jpg","ContentType":"image/jpeg","Width":1067,"Height":1600,"FileSize":342465},{"MediaUrl":"http://fishingjones.files.wordpress.com/2008/10/clown-knifefish1.jpg","ContentType":"image/jpeg","Width":1536,"Height":2048,"FileSize":655753},{"MediaUrl":"http://www.divetech.ca/images/greatalkesfish.jpg","ContentType":"image/jpeg","Width":572,"Height":828,"FileSize":385581},{"MediaUrl":"http://www.designsbysick.com/prodpics/cutefish/ContactSheet-1.jpg","ContentType":"image/jpeg","Width":600,"Height":1500,"FileSize":178036},{"MediaUrl":"http://www.acsrentals.com/acs%20rentals/images/Hawaiian_Reef_Fish_Guide.jpg","ContentType":"image/jpeg","Width":1608,"Height":2204,"FileSize":290468},{"MediaUrl":"http://petscancun.com/wp-content/uploads/2009/11/Whiskas-Fish-Chart.jpg","ContentType":"image/jpeg","Width":959,"Height":1400,"FileSize":337760},{"MediaUrl":"http://www.bedouin-lodge-dahab.com/images/red-sea-fish-fr-3.jpg","ContentType":"image/jpeg","Width":2632,"Height":3690,"FileSize":2078705},{"MediaUrl":"http://guyharveysportswear.com/blog/wp-content/uploads/2010/03/Dolphin.JPG","ContentType":"image/jpeg","Width":2187,"Height":3274,"FileSize":2144780},{"MediaUrl":"http://friendsseminarystephan.pbworks.com/f/1274835212/saltwaterfishfront.jpg","ContentType":"image/jpeg","Width":717,"Height":1051,"FileSize":154909},{"MediaUrl":"http://www.photo-dictionary.com/photofiles/list/2735/3643tropical_reef_fish.jpg","ContentType":"image/jpeg","Width":501,"Height":700,"FileSize":122668},{"MediaUrl":"http://www.webdesignhot.com/wp-content/uploads/2010/10/BigVectorCollectionofDifferentFish.jpg","ContentType":"image/jpeg","Width":775,"Height":1058,"FileSize":265410},{"MediaUrl":"http://www.twinlakesfishandgame.com/wp-content/uploads/2010/10/Fish-ID-Pics-002.jpg","ContentType":"image/jpeg","Width":960,"Height":1280,"FileSize":230052},{"MediaUrl":"http://raglanhuntfishclub.com/images/fish_1.gif","ContentType":"image/gif","Width":2480,"Height":3229,"FileSize":1720168},{"MediaUrl":"http://www.ltsd.k12.pa.us/cms/lib04/PA06000061/Centricity/Domain/169/field_guide_fish.jpg","ContentType":"image/jpeg","Width":1408,"Height":1971,"FileSize":220808},{"MediaUrl":"http://windward.hawaii.edu/facstaff/MILIEFSKY-M/hawaiireefish1.jpg","ContentType":"image/jpeg","Width":750,"Height":1155,"FileSize":363483},{"MediaUrl":"http://img72.imageshack.us/img72/7705/reddragonfish7.jpg","ContentType":"image/jpeg","Width":550,"Height":828,"FileSize":172369},{"MediaUrl":"http://www.roysfieldguides.com/images/roysfishposter.jpg","ContentType":"image/jpeg","Width":615,"Height":835,"FileSize":152845},{"MediaUrl":"http://www.malaysia.com/blog/wp-content/uploads/2009/06/fish.jpg","ContentType":"image/jpeg","Width":813,"Height":1024,"FileSize":280754},{"MediaUrl":"http://www.lakehollstein.com/images/Fresh-Fish-types-1-water.jpg","ContentType":"image/jpeg","Width":456,"Height":576,"FileSize":57204},{"MediaUrl":"http://www.siamfishingtours.com/mainartotherspecies.jpg","ContentType":"image/jpeg","Width":450,"Height":656,"FileSize":157186},{"MediaUrl":"http://cinnamonfreud.files.wordpress.com/2013/06/5-19-fish-and-chips-2.jpg","ContentType":"image/jpeg","Width":2976,"Height":3968,"FileSize":2167780},{"MediaUrl":"http://wallpaperpassion.com/upload/5220/fish-iphone-4-wallpaper.jpg","ContentType":"image/jpeg","Width":426,"Height":640,"FileSize":32062},{"MediaUrl":"http://iphonebestwallpapers.com/wp-content/uploads/2011/10/Tropical-Fish-iphone-4s-wallpaper.jpg","ContentType":"image/jpeg","Width":640,"Height":930,"FileSize":487671},{"MediaUrl":"http://fc03.deviantart.net/fs44/i/2009/138/c/c/Koi_Fish_by_bonzete.jpg","ContentType":"image/jpeg","Width":600,"Height":800,"FileSize":107836}]}